{"generated":"2026-07-08T08:28:05.925Z","source":"stockanalysis.com top-25 holdings scan","funds":{"SPY":{"tsla":1.72,"spcx":0,"cov":50.7,"aum":"$783.07B","er":"0.09%"},"VOO":{"tsla":1.88,"spcx":0,"cov":52.4,"aum":"$1.03T","er":"0.03%"},"IVV":{"tsla":1.82,"spcx":0,"cov":50.9,"aum":"$832.92B","er":"0.03%"},"VTI":{"tsla":1.69,"spcx":0,"cov":46.3,"aum":"$653.54B","er":"0.03%"},"ITOT":{"tsla":1.64,"spcx":0,"cov":45,"aum":"$91.44B","er":"0.03%"},"SCHB":{"tsla":1.55,"spcx":0,"cov":45.8,"aum":"$42.27B","er":"0.03%"},"SCHX":{"tsla":1.63,"spcx":0,"cov":48.3,"aum":"$70.83B","er":"0.03%"},"IWB":{"tsla":1.66,"spcx":0,"cov":46.8,"aum":"$47.59B","er":"0.15%"},"VV":{"tsla":1.92,"spcx":0,"cov":52.7,"aum":"$52.03B","er":"0.03%"},"QQQ":{"tsla":3.18,"spcx":0,"cov":70.7,"aum":"$480.53B","er":"0.18%"},"QQQM":{"tsla":3.18,"spcx":0,"cov":70.8,"aum":"$96.79B","er":"0.15%"},"ONEQ":{"tsla":3.26,"spcx":2.96,"cov":73,"aum":"$10.45B","er":"0.21%"},"TQQQ":{"tsla":1.03,"spcx":0,"cov":285.9,"aum":"$33.96B","er":"0.82%"},"VUG":{"tsla":3.31,"spcx":0,"cov":79,"aum":"$222.23B","er":"0.03%"},"IWF":{"tsla":3.49,"spcx":0,"cov":73,"aum":"$125.59B","er":"0.18%"},"SCHG":{"tsla":2.64,"spcx":0,"cov":71.2,"aum":"$58.37B","er":"0.04%"},"SPYG":{"tsla":1.96,"spcx":0,"cov":77,"aum":"$51.38B","er":"0.04%"},"VOOG":{"tsla":2.11,"spcx":0,"cov":78.1,"aum":"$25.60B","er":"0.07%"},"IVW":{"tsla":2.07,"spcx":0,"cov":77,"aum":"$72.99B","er":"0.18%"},"MGK":{"tsla":3.94,"spcx":0,"cov":84.8,"aum":"$33.37B","er":"0.05%"},"VONG":{"tsla":3.47,"spcx":0,"cov":76.8,"aum":"$44.05B","er":"0.06%"},"ARKK":{"tsla":10.27,"spcx":4.07,"cov":83.5,"aum":"$8.24B","er":"0.75%"},"ARKQ":{"tsla":10.23,"spcx":5.94,"cov":85.4,"aum":"$2.88B","er":"0.75%"},"ARKW":{"tsla":8.59,"spcx":3.05,"cov":84.1,"aum":"$1.64B","er":"0.76%"},"ARKX":{"tsla":2.65,"spcx":8.83,"cov":90.6,"aum":"$1.41B","er":"0.75%"},"XLY":{"tsla":18.37,"spcx":0,"cov":90,"aum":"$22.44B","er":"0.08%"},"VCR":{"tsla":17.67,"spcx":0,"cov":71,"aum":"$6.18B","er":"0.09%"},"XRT":{"tsla":0,"spcx":0,"cov":37.9,"aum":"$311.36M","er":"0.35%"},"VGT":{"tsla":0,"spcx":0,"cov":74.7,"aum":"$142.67B","er":"0.09%"},"XLK":{"tsla":0,"spcx":0,"cov":82.9,"aum":"$117.78B","er":"0.08%"},"SMH":{"tsla":0,"spcx":0,"cov":100,"aum":"$65.06B","er":"0.35%"},"SOXX":{"tsla":0,"spcx":0,"cov":96.5,"aum":"$36.93B","er":"0.34%"},"XLF":{"tsla":0,"spcx":0,"cov":77.7,"aum":"$49.53B","er":"0.08%"},"XLV":{"tsla":0,"spcx":0,"cov":85.5,"aum":"$39.24B","er":"0.08%"},"XLE":{"tsla":0,"spcx":0,"cov":100,"aum":"$39.12B","er":"0.08%"},"XLI":{"tsla":0,"spcx":0,"cov":65.6,"aum":"$31.07B","er":"0.08%"},"XLP":{"tsla":0,"spcx":0,"cov":92.7,"aum":"$14.67B","er":"0.08%"},"XLU":{"tsla":0,"spcx":0,"cov":92,"aum":"$22.55B","er":"0.08%"},"XLB":{"tsla":0,"spcx":0,"cov":98.9,"aum":"$7.83B","er":"0.08%"},"XLRE":{"tsla":0,"spcx":0,"cov":93.1,"aum":"$8.17B","er":"0.08%"},"XLC":{"tsla":0,"spcx":0,"cov":100,"aum":"$23.80B","er":"0.08%"},"VNQ":{"tsla":0,"spcx":0,"cov":73.4,"aum":"$37.70B","er":"0.13%"},"VHT":{"tsla":0,"spcx":0,"cov":73,"aum":"$16.85B","er":"0.09%"},"SCHD":{"tsla":0,"spcx":0,"cov":79,"aum":"$95.17B","er":"0.06%"},"VYM":{"tsla":0,"spcx":0,"cov":43,"aum":"$78.33B","er":"0.04%"},"VIG":{"tsla":0,"spcx":0,"cov":55.6,"aum":"$107.94B","er":"0.04%"},"DGRO":{"tsla":0,"spcx":0,"cov":47.8,"aum":"$40.58B","er":"0.08%"},"DVY":{"tsla":0,"spcx":0,"cov":38.9,"aum":"$23.09B","er":"0.38%"},"HDV":{"tsla":0,"spcx":0,"cov":81.2,"aum":"$13.57B","er":"0.08%"},"VTV":{"tsla":0,"spcx":0,"cov":38.9,"aum":"$179.59B","er":"0.03%"},"IWD":{"tsla":0,"spcx":0,"cov":40.4,"aum":"$74.84B","er":"0.18%"},"JEPI":{"tsla":0,"spcx":0,"cov":36.5,"aum":"$44.33B","er":"0.35%"},"JEPQ":{"tsla":2.4,"spcx":0,"cov":61.5,"aum":"$39.01B","er":"0.35%"},"MOAT":{"tsla":0,"spcx":0,"cov":59.2,"aum":"$11.54B","er":"0.46%"},"COWZ":{"tsla":0,"spcx":0,"cov":47.1,"aum":"$18.15B","er":"0.49%"},"DIA":{"tsla":0,"spcx":0,"cov":94.6,"aum":"$44.90B","er":"0.16%"},"RSP":{"tsla":0,"spcx":0,"cov":6.1,"aum":"$91.08B","er":"0.20%"},"IWM":{"tsla":0,"spcx":0,"cov":7.3,"aum":"$77.46B","er":"0.19%"},"VB":{"tsla":0,"spcx":0,"cov":11.4,"aum":"$79.41B","er":"0.03%"},"VO":{"tsla":0,"spcx":0,"cov":21.8,"aum":"$104.50B","er":"0.03%"},"IJH":{"tsla":0,"spcx":0,"cov":0,"aum":"$118.50B","er":"0.05%"},"IJR":{"tsla":0,"spcx":0,"cov":0,"aum":"$102.98B","er":"0.06%"},"AVUV":{"tsla":0,"spcx":0,"cov":17.9,"aum":"$28.63B","er":"0.25%"},"VXF":{"tsla":0,"spcx":0,"cov":15.7,"aum":"$30.65B","er":"0.05%"},"VBR":{"tsla":0,"spcx":0,"cov":13.5,"aum":"$35.42B","er":"0.05%"},"VXUS":{"tsla":0,"spcx":0,"cov":22.1,"aum":"$148.95B","er":"0.05%"},"VEA":{"tsla":0,"spcx":0,"cov":22.7,"aum":"$222.80B","er":"0.03%"},"VWO":{"tsla":0,"spcx":0,"cov":36.5,"aum":"$118.82B","er":"0.06%"},"IEFA":{"tsla":0,"spcx":0,"cov":22,"aum":"$181.52B","er":"0.07%"},"EFA":{"tsla":0,"spcx":0,"cov":25.6,"aum":"$77.47B","er":"0.32%"},"IEMG":{"tsla":0,"spcx":0,"cov":40.8,"aum":"$154.01B","er":"0.09%"},"IXUS":{"tsla":0,"spcx":0,"cov":21.9,"aum":"$56.64B","er":"0.07%"},"SCHF":{"tsla":0,"spcx":0,"cov":25.2,"aum":"$65.84B","er":"0.03%"},"VT":{"tsla":1.05,"spcx":0,"cov":31.5,"aum":"$74.09B","er":"0.06%"},"ACWI":{"tsla":1.09,"spcx":0,"cov":33.8,"aum":"$32.01B","er":"0.32%"},"BND":{"tsla":0,"spcx":0,"cov":10.5,"aum":"$157.85B","er":"0.03%"},"AGG":{"tsla":0,"spcx":0,"cov":11.9,"aum":"$135.94B","er":"0.03%"},"BNDX":{"tsla":0,"spcx":0,"cov":71.5,"aum":"$81.59B","er":"0.07%"},"TLT":{"tsla":0,"spcx":0,"cov":85,"aum":"$40.68B","er":"0.15%"},"SHY":{"tsla":0,"spcx":0,"cov":35.9,"aum":"$25.29B","er":"0.15%"},"SGOV":{"tsla":0,"spcx":0,"cov":100,"aum":"$95.18B","er":"0.09%"},"BIL":{"tsla":0,"spcx":0,"cov":100,"aum":"$47.84B","er":"0.14%"},"LQD":{"tsla":0,"spcx":0.25,"cov":4.6,"aum":"$29.19B","er":"0.14%"},"HYG":{"tsla":0,"spcx":0,"cov":8.2,"aum":"$16.10B","er":"0.49%"},"MUB":{"tsla":0,"spcx":0,"cov":3.9,"aum":"$45.18B","er":"0.05%"},"TSLL":{"tsla":17.4,"spcx":0,"cov":100,"aum":"$4.45B","er":"0.83%"},"TSLS":{"tsla":6.17,"spcx":0,"cov":100,"aum":"$57.93M","er":"0.95%"},"TSLZ":{"tsla":0,"spcx":0,"cov":100,"aum":"$38.41M","er":"1.05%"},"XOVR":{"tsla":0,"spcx":16.61,"cov":92.4,"aum":"$2.27B","er":"1.81%"},"OEF":{"tsla":2.39,"spcx":0,"cov":70.6,"aum":"$19.90B","er":"0.20%"},"XLG":{"tsla":2.9,"spcx":0,"cov":81.1,"aum":"$11.07B","er":"0.20%"},"SPTM":{"tsla":1.58,"spcx":0,"cov":46.8,"aum":"$13.44B","er":"0.03%"},"BKLC":{"tsla":2.02,"spcx":0,"cov":49.8,"aum":"$5.40B","er":null},"VONE":{"tsla":1.78,"spcx":0,"cov":48.7,"aum":"$7.94B","er":"0.06%"},"USMV":{"tsla":0,"spcx":0,"cov":34.1,"aum":"$23.04B","er":"0.15%"},"SCHV":{"tsla":0,"spcx":0,"cov":35.9,"aum":"$15.49B","er":"0.04%"},"SPYV":{"tsla":1.52,"spcx":0,"cov":37,"aum":"$35.18B","er":"0.04%"},"IUSV":{"tsla":1.44,"spcx":0,"cov":34.9,"aum":"$26.42B","er":"0.04%"},"IUSG":{"tsla":1.97,"spcx":0,"cov":73.1,"aum":"$31.45B","er":"0.04%"},"VBK":{"tsla":0,"spcx":0,"cov":22.7,"aum":"$23.06B","er":"0.05%"},"VOT":{"tsla":0,"spcx":0,"cov":43,"aum":"$18.86B","er":"0.05%"},"QQQE":{"tsla":0,"spcx":0,"cov":28.8,"aum":"$1.31B","er":"0.35%"},"QQQJ":{"tsla":0,"spcx":0,"cov":41.1,"aum":"$1.10B","er":"0.15%"},"VOX":{"tsla":0,"spcx":0,"cov":89.9,"aum":"$5.73B","er":"0.09%"},"VIS":{"tsla":0,"spcx":0,"cov":49.8,"aum":"$7.81B","er":"0.09%"},"VDC":{"tsla":0,"spcx":0,"cov":80.3,"aum":"$7.81B","er":"0.09%"},"VDE":{"tsla":0,"spcx":0,"cov":85.7,"aum":"$9.85B","er":"0.09%"},"VAW":{"tsla":0,"spcx":0,"cov":76.9,"aum":"$3.00B","er":"0.09%"},"FTEC":{"tsla":0,"spcx":0,"cov":75.2,"aum":"$20.15B","er":"0.08%"},"IYW":{"tsla":0,"spcx":0,"cov":83.4,"aum":"$24.25B","er":"0.38%"},"IGV":{"tsla":0,"spcx":0,"cov":85.1,"aum":"$15.91B","er":"0.39%"},"ITA":{"tsla":0,"spcx":0,"cov":96.1,"aum":"$13.91B","er":"0.38%"},"XAR":{"tsla":0,"spcx":0,"cov":71,"aum":"$6.31B","er":"0.35%"},"PPA":{"tsla":0,"spcx":0,"cov":82.5,"aum":"$8.02B","er":"0.58%"},"UFO":{"tsla":0,"spcx":4.92,"cov":85.2,"aum":"$1.05B","er":"0.75%"},"ARKF":{"tsla":0,"spcx":0,"cov":89.8,"aum":"$744.60M","er":"0.75%"},"NOBL":{"tsla":0,"spcx":0,"cov":39.9,"aum":"$11.44B","er":"0.35%"},"SDY":{"tsla":0,"spcx":0,"cov":36.7,"aum":"$21.10B","er":"0.35%"},"SPHD":{"tsla":0,"spcx":0,"cov":62.5,"aum":"$3.28B","er":"0.30%"},"DGRW":{"tsla":0,"spcx":0,"cov":61.3,"aum":"$16.72B","er":"0.28%"},"SSO":{"tsla":1.19,"spcx":0,"cov":159.2,"aum":"$7.51B","er":"0.87%"},"UPRO":{"tsla":0.85,"spcx":0,"cov":273.3,"aum":"$5.13B","er":"0.89%"},"SPXL":{"tsla":1.33,"spcx":0,"cov":72.4,"aum":"$6.18B","er":"0.84%"},"QLD":{"tsla":2.17,"spcx":0,"cov":167.4,"aum":"$13.20B","er":"0.95%"},"SQQQ":{"tsla":0,"spcx":0,"cov":-300,"aum":"$2.46B","er":"0.95%"},"SDS":{"tsla":0,"spcx":0,"cov":-200,"aum":"$438.20M","er":"0.91%"},"SPXS":{"tsla":0,"spcx":0,"cov":100,"aum":"$411.71M","er":"1.04%"},"VEU":{"tsla":0,"spcx":0,"cov":23.2,"aum":"$64.60B","er":"0.04%"},"VGIT":{"tsla":0,"spcx":0,"cov":41.4,"aum":"$40.97B","er":"0.03%"},"VGSH":{"tsla":0,"spcx":0,"cov":32.3,"aum":"$29.36B","er":"0.03%"},"VGLT":{"tsla":0,"spcx":0,"cov":43.4,"aum":"$10.37B","er":"0.03%"},"VTEB":{"tsla":0,"spcx":0,"cov":3.8,"aum":"$45.04B","er":"0.03%"},"SCHZ":{"tsla":0,"spcx":0,"cov":9.2,"aum":"$10.35B","er":"0.03%"},"FBND":{"tsla":0,"spcx":0,"cov":31.1,"aum":"$26.04B","er":"0.36%"},"FXAIX":{"tsla":1.92,"spcx":0,"cov":100,"src":"nport","asof":"2026-02-28","aum":null,"er":null},"VFIAX":{"tsla":1.87,"spcx":0,"cov":100,"src":"nport","asof":"2026-03-31","aum":null,"er":null},"SWPPX":{"tsla":1.73,"spcx":0,"cov":100,"src":"nport","asof":"2026-04-30","aum":null,"er":null},"VTSAX":{"tsla":1.67,"spcx":0,"cov":100,"src":"nport","asof":"2026-03-31","aum":null,"er":null},"FSKAX":{"tsla":1.7,"spcx":0,"cov":100,"src":"nport","asof":"2026-02-28","aum":null,"er":null},"FZROX":{"tsla":1.54,"spcx":0,"cov":100,"src":"nport","asof":"2026-04-30","aum":null,"er":null},"SWTSX":{"tsla":1.54,"spcx":0,"cov":100,"src":"nport","asof":"2026-04-30","aum":null,"er":null},"FBGRX":{"tsla":1.4,"spcx":3.28,"cov":100,"src":"nport","asof":"2026-04-30","aum":null,"er":null},"AGTHX":{"tsla":2.59,"spcx":0,"cov":100,"src":"nport","asof":"2026-02-28","aum":null,"er":null},"VTWAX":{"tsla":0.97,"spcx":0,"cov":100,"src":"nport","asof":"2026-04-30","aum":null,"er":null},"VBTLX":{"tsla":0,"spcx":0,"cov":100,"src":"nport","asof":"2026-03-31","aum":null,"er":null},"FXNAX":{"tsla":0,"spcx":0,"cov":100,"src":"nport","asof":"2026-02-28","aum":null,"er":null},"VBIAX":{"tsla":1,"spcx":0,"cov":100,"src":"nport","asof":"2026-03-31","aum":null,"er":null},"VWELX":{"tsla":1.05,"spcx":0,"cov":100,"src":"nport","asof":"2026-02-28","aum":null,"er":null},"BPTRX":{"tsla":23.16,"spcx":37.55,"cov":100,"src":"nport","asof":"2026-03-31","aum":null,"er":null},"BFGFX":{"tsla":5.99,"spcx":21.26,"cov":100,"src":"nport","asof":"2026-03-31","aum":null,"er":null},"FNILX":{"tsla":1.7,"spcx":0,"cov":100,"src":"nport","asof":"2026-04-30","aum":null,"er":null},"FTIHX":{"tsla":0,"spcx":0,"cov":100,"src":"nport","asof":"2026-04-30","aum":null,"er":null},"FZILX":{"tsla":0,"spcx":0,"cov":100,"src":"nport","asof":"2026-04-30","aum":null,"er":null},"FCNTX":{"tsla":0.07,"spcx":5.1,"cov":100,"src":"nport","asof":"2026-03-31","aum":null,"er":null},"FDGRX":{"tsla":1.86,"spcx":2.85,"cov":100,"src":"nport","asof":"2026-02-28","aum":null,"er":null},"TRBCX":{"tsla":2.71,"spcx":0,"cov":100,"src":"nport","asof":"2026-03-31","aum":null,"er":null},"DODGX":{"tsla":0,"spcx":0,"cov":100,"src":"nport","asof":"2026-03-31","aum":null,"er":null},"PRWCX":{"tsla":0,"spcx":0,"cov":100,"src":"nport","asof":"2026-03-31","aum":null,"er":null}}}